bootstrapform_jinja/__init__.py
bootstrapform_jinja/apps.py
bootstrapform_jinja/config.py
bootstrapform_jinja/models.py
bootstrapform_jinja/version.py
bootstrapform_jinja/templates/bootstrapform/field.jinja
bootstrapform_jinja/templates/bootstrapform/field_macros.jinja
bootstrapform_jinja/templates/bootstrapform/form.jinja
bootstrapform_jinja/templates/bootstrapform/formset.jinja
bootstrapform_jinja/templatetags/__init__.py
bootstrapform_jinja/templatetags/bootstrap.py
django_jinja_bootstrap_form-4.5.0.dist-info/LICENSE
django_jinja_bootstrap_form-4.5.0.dist-info/METADATA
django_jinja_bootstrap_form-4.5.0.dist-info/WHEEL
django_jinja_bootstrap_form-4.5.0.dist-info/top_level.txt
django_jinja_bootstrap_form-4.5.0.dist-info/zip-safe
django_jinja_bootstrap_form-4.5.0.dist-info/RECORD
